Metadata-Version: 1.0
Name: datatoaster
Version: 0.1.0
Summary: A Python library that can convert raw data to chart data
Home-page: https://github.com/abc612008/datatoaster
Author: Harry Yu
Author-email: harryyunull@gmail.com
License: MIT
Platform: UNKNOWN
